[
  {
    "registrationNo": "CAH-4897",
    "lastDateOfChange": "21/03/2024",
    "meterReading": 130743,
    "runningDifference": 2876,
    "description": "165-70 R 13 ",
    "remarks": null
  },
  {
    "registrationNo": "MNS-17-900",
    "lastDateOfChange": "19/06/2023",
    "meterReading": 272474,
    "runningDifference": 67471,
    "description": "215-70-R 15",
    "remarks": "01 tyre issued 13/08/2023 (280874) "
  },
  {
    "registrationNo": "MNS-17-913",
    "lastDateOfChange": "28/02/2024",
    "meterReading": 182542,
    "runningDifference": 3344,
    "description": "6-50-R 16",
    "remarks": null
  },
  {
    "registrationNo": "MNS-18-9047",
    "lastDateOfChange": "16/11/2023",
    "meterReading": 416799,
    "runningDifference": 26705,
    "description": "215-70-R 15",
    "remarks": null
  },
  {
    "registrationNo": "MNS-19-9027",
    "lastDateOfChange": "19/09/2023",
    "meterReading": 164342,
    "runningDifference": 21881,
    "description": "185 R 14 C",
    "remarks": "01 tyre issued 07/08/2023 (159555)"
  },
  {
    "registrationNo": "MNS-19-9042",
    "lastDateOfChange": 45149,
    "meterReading": 361810,
    "runningDifference": 48678,
    "description": "215-70-R 15",
    "remarks": null
  },
  {
    "registrationNo": "MNS-19-913",
    "lastDateOfChange": "20/09/2023",
    "meterReading": 171293,
    "runningDifference": 15952,
    "description": "215-70-R 15",
    "remarks": null
  },
  {
    "registrationNo": "MNS-19-916",
    "lastDateOfChange": "13/08/2023",
    "meterReading": 220356,
    "runningDifference": 31849,
    "description": "6-50-R 16",
    "remarks": null
  },
  {
    "registrationNo": "MNS-17-923",
    "lastDateOfChange": "25/04/2023",
    "meterReading": 212611,
    "runningDifference": 45220,
    "description": "6-50-R 16",
    "remarks": null
  },
  {
    "registrationNo": "CAE-5489",
    "lastDateOfChange": 45355,
    "meterReading": 519618,
    "runningDifference": 7561,
    "description": "215-70-R 15",
    "remarks": "01 tyre issued 13/08/2023 (384784) "
  },
  {
    "registrationNo": "CAF-3562",
    "lastDateOfChange": "27/02/2023",
    "meterReading": 58894,
    "runningDifference": 32264,
    "description": "185 R 14 C",
    "remarks": null
  },
  {
    "registrationNo": "MNS-18-9007",
    "lastDateOfChange": 45445,
    "meterReading": 228445,
    "runningDifference": null,
    "description": "195.R15 FR",
    "remarks": "04 tyre changed on 07/10/2022 (162608)--165.70.13 RR"
  },
  {
    "registrationNo": "CAJ-6014",
    "lastDateOfChange": 45386,
    "meterReading": 80680,
    "runningDifference": 415,
    "description": "175-70-R14",
    "remarks": null
  },
  {
    "registrationNo": "BF-9583",
    "lastDateOfChange": 44473,
    "meterReading": 92527,
    "runningDifference": -73888,
    "description": "7.50-R 16",
    "remarks": null
  },
  {
    "registrationNo": "MNS-18-963",
    "lastDateOfChange": 45148,
    "meterReading": 205850,
    "runningDifference": 19966,
    "description": "6-50-R 16",
    "remarks": null
  },
  {
    "registrationNo": "CAG-7225",
    "lastDateOfChange": 45355,
    "meterReading": 268762,
    "runningDifference": 5416,
    "description": "215-70-R 15",
    "remarks": "01 tyre issued 13/08/2023 (169150) ST"
  },
  {
    "registrationNo": "CAG-7243",
    "lastDateOfChange": "24/02/2024",
    "meterReading": 262473,
    "runningDifference": 19749,
    "description": "215-70-R 15",
    "remarks": "01 tyre issued 13/08/2023 (178748) ST"
  },
  {
    "registrationNo": "MNS-19-923",
    "lastDateOfChange": "18/7/2022",
    "meterReading": 242418,
    "runningDifference": 39368,
    "description": "215-70-R 15",
    "remarks": null
  },
  {
    "registrationNo": "MNS-18-996",
    "lastDateOfChange": 45352,
    "meterReading": 234122,
    "runningDifference": 10055,
    "description": "215-70-R 15",
    "remarks": "04 tyre issued 09-02-2023 (202718)"
  },
  {
    "registrationNo": "MNS-18-961",
    "lastDateOfChange": "13/12/2023",
    "meterReading": 329495,
    "runningDifference": 12702,
    "description": "215-70-R 15",
    "remarks": null
  },
  {
    "registrationNo": "MNS-20-9023",
    "lastDateOfChange": 45265,
    "meterReading": 179709,
    "runningDifference": 38414,
    "description": "215-70-R 15",
    "remarks": "01 tyre change on 19-07-2022"
  },
  {
    "registrationNo": "CAD-092",
    "lastDateOfChange": null,
    "meterReading": null,
    "runningDifference": 13887,
    "description": "215-70-R 15",
    "remarks": null
  },
  {
    "registrationNo": "CH-1329",
    "lastDateOfChange": null,
    "meterReading": null,
    "runningDifference": 0,
    "description": "215-70-R 15",
    "remarks": null
  },
  {
    "registrationNo": "CAP-3103",
    "lastDateOfChange": "27/03/2024",
    "meterReading": 48036,
    "runningDifference": 3669,
    "description": "175-70-R14 C",
    "remarks": "04 tyre change on 13/11/2024 (18298)"
  },
  {
    "registrationNo": "CAA-4427",
    "lastDateOfChange": "13/01/2024",
    "meterReading": 181485,
    "runningDifference": 13806,
    "description": "215-70-R 15",
    "remarks": null
  },
  {
    "registrationNo": "CAD-5208",
    "lastDateOfChange": "24/05/2023",
    "meterReading": 136175,
    "runningDifference": 42987,
    "description": "215-70-R 15",
    "remarks": null
  },
  {
    "registrationNo": "MNS-17-920",
    "lastDateOfChange": 44994,
    "meterReading": 388515,
    "runningDifference": 29445,
    "description": "215-70-R 15",
    "remarks": null
  },
  {
    "registrationNo": "CAF-3564",
    "lastDateOfChange": "24/12/2023",
    "meterReading": 97996,
    "runningDifference": 7159,
    "description": "185 R 14 C",
    "remarks": null
  },
  {
    "registrationNo": "CAA-3745",
    "lastDateOfChange": "15/08/2023",
    "meterReading": 152735,
    "runningDifference": 27769,
    "description": "215-70-R 15",
    "remarks": null
  },
  {
    "registrationNo": "MNS-17-901",
    "lastDateOfChange": 45234,
    "meterReading": 182355,
    "runningDifference": 21701,
    "description": "215-70-R 15",
    "remarks": null
  },
  {
    "registrationNo": "MNS-17-902",
    "lastDateOfChange": 45269,
    "meterReading": 154765,
    "runningDifference": 13848,
    "description": "215-70-R 15",
    "remarks": "02 tyre issued 07/08/2023 (152187)"
  },
  {
    "registrationNo": "MNS-17-910",
    "lastDateOfChange": "31/08/2023",
    "meterReading": 179864,
    "runningDifference": 19626,
    "description": "215-70-R 15",
    "remarks": null
  },
  {
    "registrationNo": "MNS-17-914",
    "lastDateOfChange": "18/05/2022",
    "meterReading": 187176,
    "runningDifference": 40094,
    "description": "215-70-R 15",
    "remarks": null
  },
  {
    "registrationNo": "MNS-17-918",
    "lastDateOfChange": "18/05/2023",
    "meterReading": 234137,
    "runningDifference": 31869,
    "description": "215-70-R 15",
    "remarks": null
  },
  {
    "registrationNo": "MNS-18-9003",
    "lastDateOfChange": "29/11/2022",
    "meterReading": 179129,
    "runningDifference": 35223,
    "description": "215-70-R 15",
    "remarks": null
  },
  {
    "registrationNo": "MNS-18-9009",
    "lastDateOfChange": "13/07/2023",
    "meterReading": 132340,
    "runningDifference": 15517,
    "description": "185 R 14 C",
    "remarks": null
  },
  {
    "registrationNo": "MNS-18-9037",
    "lastDateOfChange": 45149,
    "meterReading": 228260,
    "runningDifference": 9060,
    "description": "215-70-R 15",
    "remarks": null
  },
  {
    "registrationNo": "MNS-18-9040",
    "lastDateOfChange": "24/05/2023",
    "meterReading": 185415,
    "runningDifference": 19269,
    "description": "215-70-R 15",
    "remarks": null
  },
  {
    "registrationNo": "MNS-18-9050",
    "lastDateOfChange": "18/02/2024",
    "meterReading": 235469,
    "runningDifference": 6328,
    "description": "215-70-R 15",
    "remarks": null
  },
  {
    "registrationNo": "MNS-18-950",
    "lastDateOfChange": 45109,
    "meterReading": 157916,
    "runningDifference": 39181,
    "description": "6-50-R 16",
    "remarks": "02 tyre issued 02/07/2021 (116550)"
  },
  {
    "registrationNo": "MNS-18-955",
    "lastDateOfChange": 45109,
    "meterReading": 139248,
    "runningDifference": 23741,
    "description": "6-50-R 16",
    "remarks": "02 tyre issued 13/09/2022 (130774)"
  },
  {
    "registrationNo": "MNS-18-966",
    "lastDateOfChange": "14/01/2024",
    "meterReading": 183872,
    "runningDifference": 7232,
    "description": "6-50-R 16",
    "remarks": null
  },
  {
    "registrationNo": "MNS-19-900",
    "lastDateOfChange": "16/11/2023",
    "meterReading": 159791,
    "runningDifference": 12162,
    "description": "215-70-R 15",
    "remarks": null
  },
  {
    "registrationNo": "MNS-19-9003",
    "lastDateOfChange": "17/07/2023",
    "meterReading": 147041,
    "runningDifference": 33672,
    "description": "215-70-R 15",
    "remarks": null
  },
  {
    "registrationNo": "MNS-19-9009",
    "lastDateOfChange": "24/02/2023",
    "meterReading": 130875,
    "runningDifference": 28616,
    "description": "215-70-R 15",
    "remarks": null
  },
  {
    "registrationNo": "MNS-19-9049",
    "lastDateOfChange": "22/10/2023",
    "meterReading": 199412,
    "runningDifference": 24582,
    "description": "215-70-R 15",
    "remarks": null
  },
  {
    "registrationNo": "MNS-19-9050",
    "lastDateOfChange": 45058,
    "meterReading": 179790,
    "runningDifference": 14582,
    "description": "215-70-R 15",
    "remarks": null
  },
  {
    "registrationNo": "MNS-20-9010",
    "lastDateOfChange": 44930,
    "meterReading": 114347,
    "runningDifference": 38369,
    "description": "215-70-R 15",
    "remarks": null
  },
  {
    "registrationNo": "MNS-20-9013",
    "lastDateOfChange": 45058,
    "meterReading": 145997,
    "runningDifference": 11054,
    "description": "215-70-R 15",
    "remarks": null
  },
  {
    "registrationNo": "MNS-20-9015",
    "lastDateOfChange": 45148,
    "meterReading": 95151,
    "runningDifference": 11727,
    "description": "215-70-R 15",
    "remarks": null
  },
  {
    "registrationNo": "MNS-20-9020",
    "lastDateOfChange": "29/01/2024",
    "meterReading": 225510,
    "runningDifference": 10270,
    "description": "215-70-R 15",
    "remarks": null
  },
  {
    "registrationNo": "CAA-4451",
    "lastDateOfChange": 45269,
    "meterReading": 124742,
    "runningDifference": 22073,
    "description": "215-70-R 15",
    "remarks": null
  },
  {
    "registrationNo": "CAA-4392",
    "lastDateOfChange": "27/02/2024",
    "meterReading": 87262,
    "runningDifference": 3056,
    "description": "215-70-R 15",
    "remarks": null
  },
  {
    "registrationNo": "CAA-4395",
    "lastDateOfChange": "14/09/2023",
    "meterReading": 88540,
    "runningDifference": 22791,
    "description": "215-70-R 15",
    "remarks": "04 tyre issued 15/01/2022 (44261)--02 tyre isued on 07/08/2023 (84499)"
  },
  {
    "registrationNo": "CAC-5071",
    "lastDateOfChange": 45599,
    "meterReading": 89645,
    "runningDifference": 1777,
    "description": "215-70-R 15",
    "remarks": null
  },
  {
    "registrationNo": "MNS-18-932",
    "lastDateOfChange": "23/10/2023",
    "meterReading": 200892,
    "runningDifference": 11597,
    "description": "6-50-R 16",
    "remarks": null
  },
  {
    "registrationNo": "CAD-6019",
    "lastDateOfChange": "22/03/2024",
    "meterReading": 86992,
    "runningDifference": 1313,
    "description": "215-70-R 15",
    "remarks": null
  },
  {
    "registrationNo": "CAH-4901",
    "lastDateOfChange": "19/11/2023",
    "meterReading": 91377,
    "runningDifference": 13506,
    "description": "165-70 R 13 ",
    "remarks": null
  },
  {
    "registrationNo": "CAF-6784",
    "lastDateOfChange": "21/03/2023",
    "meterReading": 93520,
    "runningDifference": 40298,
    "description": "215-70-R 15",
    "remarks": null
  },
  {
    "registrationNo": "MNS-19-9017",
    "lastDateOfChange": 45292,
    "meterReading": 160665,
    "runningDifference": 6928,
    "description": "215-70-R 15",
    "remarks": null
  },
  {
    "registrationNo": "CAG-7236",
    "lastDateOfChange": 45292,
    "meterReading": 147455,
    "runningDifference": 20295,
    "description": "215-70-R 15",
    "remarks": "01 tyre issued 08/02/2023 (65141)"
  },
  {
    "registrationNo": "CAJ-8046",
    "lastDateOfChange": "16/10/2023",
    "meterReading": 89072,
    "runningDifference": 47741,
    "description": "215-70-R 15",
    "remarks": null
  },
  {
    "registrationNo": "CAJ-8055",
    "lastDateOfChange": 45272,
    "meterReading": 100840,
    "runningDifference": 27268,
    "description": "215-70-R 15",
    "remarks": null
  },
  {
    "registrationNo": "CAN-1852",
    "lastDateOfChange": 45148,
    "meterReading": 30874,
    "runningDifference": 15507,
    "description": "175-70-R14 C",
    "remarks": null
  },
  {
    "registrationNo": "CAL-8450 ",
    "lastDateOfChange": null,
    "meterReading": null,
    "runningDifference": 38140,
    "description": "215-70-R 15",
    "remarks": null
  },
  {
    "registrationNo": "MNS-18-9031",
    "lastDateOfChange": 45241,
    "meterReading": 199688,
    "runningDifference": 16152,
    "description": "185 R 14 C",
    "remarks": "04 tyre issued 13-12-2022 (168115)"
  },
  {
    "registrationNo": "CAP-507",
    "lastDateOfChange": "29/01/2024",
    "meterReading": 28652,
    "runningDifference": 6152,
    "description": "175-70-R14 C",
    "remarks": null
  },
  {
    "registrationNo": "CAP-494",
    "lastDateOfChange": null,
    "meterReading": null,
    "runningDifference": 37777,
    "description": "215-70-R 15",
    "remarks": null
  },
  {
    "registrationNo": "CAP-3089",
    "lastDateOfChange": null,
    "meterReading": null,
    "runningDifference": 23375,
    "description": "175-70-R14 C",
    "remarks": null
  },
  {
    "registrationNo": "CAP-3101",
    "lastDateOfChange": 45353,
    "meterReading": 14904,
    "runningDifference": 3986,
    "description": "175-70-R14 C",
    "remarks": null
  },
  {
    "registrationNo": "CAP-3099",
    "lastDateOfChange": null,
    "meterReading": null,
    "runningDifference": 19000,
    "description": "175-70-R14 C",
    "remarks": null
  },
  {
    "registrationNo": "LD-1460",
    "lastDateOfChange": null,
    "meterReading": null,
    "runningDifference": 25871,
    "description": "215-70-R15",
    "remarks": null
  },
  {
    "registrationNo": "CAD-382",
    "lastDateOfChange": null,
    "meterReading": null,
    "runningDifference": 4457,
    "description": "21-70-R15",
    "remarks": null
  },
  {
    "registrationNo": "LD-2370",
    "lastDateOfChange": null,
    "meterReading": null,
    "runningDifference": 4385,
    "description": "215-70-R 15",
    "remarks": null
  },
  {
    "registrationNo": "CAD-984",
    "lastDateOfChange": null,
    "meterReading": null,
    "runningDifference": 3399,
    "description": "215-70-R 15",
    "remarks": null
  },
  {
    "registrationNo": "CH-1337",
    "lastDateOfChange": null,
    "meterReading": null,
    "runningDifference": 4685,
    "description": "215-70-R 15",
    "remarks": null
  },
  {
    "registrationNo": "CH-1452",
    "lastDateOfChange": null,
    "meterReading": null,
    "runningDifference": 0,
    "description": "215-70-R 15",
    "remarks": null
  },
  {
    "registrationNo": "CAA - 3748",
    "lastDateOfChange": "27/02/2023",
    "meterReading": 194535,
    "runningDifference": 6255,
    "description": "215-70-R 15",
    "remarks": "01 Spare Tyre issued MR 186815 08-01-2024"
  },
  {
    "registrationNo": "MNS-17-908",
    "lastDateOfChange": "27/02/2024",
    "meterReading": 244678,
    "runningDifference": 1821,
    "description": "215-70-R 15",
    "remarks": null
  },
  {
    "registrationNo": "MNS-17-921",
    "lastDateOfChange": "28/02/2024",
    "meterReading": 177035,
    "runningDifference": 2788,
    "description": "215-70-R 15",
    "remarks": null
  },
  {
    "registrationNo": "MNS-18-9001",
    "lastDateOfChange": "13/12/2023",
    "meterReading": 214840,
    "runningDifference": 14235,
    "description": "215-70-R 15",
    "remarks": null
  },
  {
    "registrationNo": "MNS-18-9002",
    "lastDateOfChange": "19/09/2023",
    "meterReading": 175602,
    "runningDifference": 25568,
    "description": "215-70-R 15",
    "remarks": null
  },
  {
    "registrationNo": "MNS-18-9014",
    "lastDateOfChange": 45109,
    "meterReading": 139985,
    "runningDifference": 35442,
    "description": "215-70-R 15",
    "remarks": null
  },
  {
    "registrationNo": "MNS-18-9024",
    "lastDateOfChange": 45148,
    "meterReading": 168554,
    "runningDifference": 17202,
    "description": "215-70-R 15",
    "remarks": null
  },
  {
    "registrationNo": "MNS-18-9026",
    "lastDateOfChange": "17/11/2022",
    "meterReading": 112404,
    "runningDifference": 34341,
    "description": "185 R 14 C",
    "remarks": null
  },
  {
    "registrationNo": "MNS-18-9030",
    "lastDateOfChange": 45210,
    "meterReading": 138416,
    "runningDifference": 7292,
    "description": "185 R 14 C",
    "remarks": null
  },
  {
    "registrationNo": "MNS-18-9033",
    "lastDateOfChange": "101/12/2023",
    "meterReading": 139649,
    "runningDifference": 9452,
    "description": "185 R 14 C",
    "remarks": "01 tyre issued 09/06/2023 (99325)"
  },
  {
    "registrationNo": "MNS-18-9042",
    "lastDateOfChange": "16/04/2023",
    "meterReading": 171972,
    "runningDifference": 33883,
    "description": "215-70-R 15",
    "remarks": null
  },
  {
    "registrationNo": "MNS-18-9044",
    "lastDateOfChange": "23/10/2023",
    "meterReading": 185029,
    "runningDifference": 10956,
    "description": "215-70-R 15",
    "remarks": null
  },
  {
    "registrationNo": "MNS-18-9046",
    "lastDateOfChange": 45292,
    "meterReading": 168076,
    "runningDifference": 6739,
    "description": "215-70-R 15",
    "remarks": null
  },
  {
    "registrationNo": "MNS-18-9052",
    "lastDateOfChange": "16/04/2023",
    "meterReading": 218731,
    "runningDifference": 27462,
    "description": "215-70-R 15",
    "remarks": null
  },
  {
    "registrationNo": "MNS-18-938",
    "lastDateOfChange": 45568,
    "meterReading": 115636,
    "runningDifference": 987,
    "description": "6-50-R 16",
    "remarks": null
  },
  {
    "registrationNo": "MNS-18-958",
    "lastDateOfChange": "24/10/2022",
    "meterReading": 133114,
    "runningDifference": 42351,
    "description": "215-70-R 15",
    "remarks": null
  },
  {
    "registrationNo": "MNS-19-9005",
    "lastDateOfChange": 45211,
    "meterReading": 151400,
    "runningDifference": 6700,
    "description": "185 R 14 C",
    "remarks": null
  },
  {
    "registrationNo": "MNS-19-9013",
    "lastDateOfChange": "18/09/2023",
    "meterReading": 175192,
    "runningDifference": 22298,
    "description": "215-70-R 15",
    "remarks": null
  },
  {
    "registrationNo": "MNS-19-9020",
    "lastDateOfChange": "15/03/2023",
    "meterReading": 135240,
    "runningDifference": null,
    "description": "215-70-R 15",
    "remarks": null
  },
  {
    "registrationNo": "MNS-19-9033",
    "lastDateOfChange": "28/02/2024",
    "meterReading": 123482,
    "runningDifference": 2559,
    "description": "185 R 14 C",
    "remarks": null
  },
  {
    "registrationNo": "MNS-19-9034",
    "lastDateOfChange": "18/09/2023",
    "meterReading": 80467,
    "runningDifference": 18812,
    "description": "185 R 14 C",
    "remarks": null
  },
  {
    "registrationNo": "MNS-19-9037",
    "lastDateOfChange": 45232,
    "meterReading": 108455,
    "runningDifference": 34466,
    "description": "185 R 14 C",
    "remarks": null
  },
  {
    "registrationNo": "MNS-19-9041",
    "lastDateOfChange": 45241,
    "meterReading": 188348,
    "runningDifference": 16886,
    "description": "215-70-R 15",
    "remarks": null
  },
  {
    "registrationNo": "MNS-19-9045",
    "lastDateOfChange": 45179,
    "meterReading": 156240,
    "runningDifference": 17275,
    "description": "215-70-R 15",
    "remarks": null
  },
  {
    "registrationNo": "MNS-20-9004",
    "lastDateOfChange": "16/04/2023",
    "meterReading": 129748,
    "runningDifference": 37846,
    "description": "215-70-R 15",
    "remarks": null
  },
  {
    "registrationNo": "MNS-20-9008",
    "lastDateOfChange": 45210,
    "meterReading": 194545,
    "runningDifference": 19704,
    "description": "215-70-R 15",
    "remarks": null
  },
  {
    "registrationNo": "MNS-20-9009",
    "lastDateOfChange": 44997,
    "meterReading": 174282,
    "runningDifference": 18660,
    "description": "215-70-R 15",
    "remarks": null
  },
  {
    "registrationNo": "CAC-3411",
    "lastDateOfChange": "23/03/2022",
    "meterReading": 39400,
    "runningDifference": 28540,
    "description": "185 R 14 C",
    "remarks": null
  },
  {
    "registrationNo": "CAC-5069",
    "lastDateOfChange": "14/01/2024",
    "meterReading": 92479,
    "runningDifference": 5117,
    "description": "215-70-R 15",
    "remarks": null
  },
  {
    "registrationNo": "CAD-5226",
    "lastDateOfChange": 44873,
    "meterReading": 45633,
    "runningDifference": 44638,
    "description": "215-70-R 15",
    "remarks": "01 Spare Tyre issued MR 87171 08-01-2024"
  },
  {
    "registrationNo": "CAD-6067",
    "lastDateOfChange": 44569,
    "meterReading": 41819,
    "runningDifference": 40127,
    "description": "215-70-R 15",
    "remarks": null
  },
  {
    "registrationNo": "CAD-6001",
    "lastDateOfChange": 45211,
    "meterReading": 94739,
    "runningDifference": 7179,
    "description": "215-70-R 15",
    "remarks": null
  },
  {
    "registrationNo": "CAF-6788 ",
    "lastDateOfChange": "16/04/2023",
    "meterReading": 77687,
    "runningDifference": 31918,
    "description": "215-70-R 15",
    "remarks": "01 Spare Tyre issued MR 103946  08-01-2024"
  },
  {
    "registrationNo": "CAG-1144  ",
    "lastDateOfChange": "26/03/2024",
    "meterReading": 201047,
    "runningDifference": 578,
    "description": "215-70-R 15",
    "remarks": null
  },
  {
    "registrationNo": "CAF-6806 ",
    "lastDateOfChange": "15/11/2023",
    "meterReading": 95919,
    "runningDifference": 13900,
    "description": "215-70-R 15",
    "remarks": null
  },
  {
    "registrationNo": "CAD-5221",
    "lastDateOfChange": "27/02/2024",
    "meterReading": 121588,
    "runningDifference": 2566,
    "description": "215-70-R 15",
    "remarks": null
  },
  {
    "registrationNo": "CAA-4406",
    "lastDateOfChange": "15/06/2023",
    "meterReading": 108451,
    "runningDifference": 35571,
    "description": "215-70-R 15",
    "remarks": "01 Spare Tyre issued MR 134509 08-01-2024"
  },
  {
    "registrationNo": "MNS-18-9053",
    "lastDateOfChange": "14/01/2024",
    "meterReading": 312780,
    "runningDifference": 8243,
    "description": "215-70-R 15",
    "remarks": null
  },
  {
    "registrationNo": "CAJ-6024",
    "lastDateOfChange": "23/11/2022",
    "meterReading": 25840,
    "runningDifference": 38265,
    "description": "175-70-R14",
    "remarks": "02 tyre change on 22/08/2022 MR (16479 Km)"
  },
  {
    "registrationNo": "CAK-9782",
    "lastDateOfChange": "18/09/2023",
    "meterReading": 41467,
    "runningDifference": 18791,
    "description": "215-70-R 15",
    "remarks": null
  },
  {
    "registrationNo": "CAK-9775",
    "lastDateOfChange": "27/02/2024",
    "meterReading": 74627,
    "runningDifference": 2614,
    "description": "215-70-R 15",
    "remarks": "04 tyre change on 03-07-2022 MR (25800 Km)"
  },
  {
    "registrationNo": "MNS-18-9025",
    "lastDateOfChange": "16/11/2022",
    "meterReading": 308840,
    "runningDifference": 31377,
    "description": "215-70-R 15",
    "remarks": null
  },
  {
    "registrationNo": "CAP-502",
    "lastDateOfChange": null,
    "meterReading": null,
    "runningDifference": 34623,
    "description": "175-70-R14 C",
    "remarks": null
  },
  {
    "registrationNo": "MNS-19-908",
    "lastDateOfChange": 45174,
    "meterReading": 238647,
    "runningDifference": 23294,
    "description": "215-70-R 15",
    "remarks": "01 Tyre as a stepny MR 198263 11-10-2022"
  },
  {
    "registrationNo": "LD-1458",
    "lastDateOfChange": null,
    "meterReading": null,
    "runningDifference": 27649,
    "description": "215-70-R 15",
    "remarks": null
  },
  {
    "registrationNo": "LD-1456",
    "lastDateOfChange": null,
    "meterReading": null,
    "runningDifference": 26308,
    "description": "215-70-R 15",
    "remarks": null
  },
  {
    "registrationNo": "MNS 20-900",
    "lastDateOfChange": null,
    "meterReading": null,
    "runningDifference": 58876,
    "description": "185 R 14 C",
    "remarks": null
  },
  {
    "registrationNo": "CAD-057",
    "lastDateOfChange": null,
    "meterReading": null,
    "runningDifference": 11702,
    "description": "215-70-R 15",
    "remarks": null
  },
  {
    "registrationNo": "LD-2369",
    "lastDateOfChange": null,
    "meterReading": null,
    "runningDifference": 4046,
    "description": "215-70-R 15",
    "remarks": null
  },
  {
    "registrationNo": "CH-1338",
    "lastDateOfChange": null,
    "meterReading": null,
    "runningDifference": 3281,
    "description": null,
    "remarks": null
  },
  {
    "registrationNo": "CAG-059",
    "lastDateOfChange": "23/10/2023",
    "meterReading": 206412,
    "runningDifference": 51622,
    "description": "215-70-R 15",
    "remarks": "01 Tyre as a stepny 17-06-2023 (171522)"
  },
  {
    "registrationNo": "MNS-18-954",
    "lastDateOfChange": "18/02/2024",
    "meterReading": 240111,
    "runningDifference": 4282,
    "description": "6-50-R 16",
    "remarks": null
  },
  {
    "registrationNo": "MNS-17-907",
    "lastDateOfChange": "17/12/2023",
    "meterReading": 305513,
    "runningDifference": 11932,
    "description": "215-70-R 15",
    "remarks": null
  },
  {
    "registrationNo": "MNS-18-9006",
    "lastDateOfChange": "28/12/2023",
    "meterReading": 0,
    "runningDifference": null,
    "description": "165.70.13 RR\r\n215.70 R15 FR",
    "remarks": "02 tyre 195-R15 changed on 08-08-2023        "
  },
  {
    "registrationNo": "MNS-18-9034",
    "lastDateOfChange": "23/09/2023",
    "meterReading": 149935,
    "runningDifference": 16065,
    "description": "185 R 14 C",
    "remarks": null
  },
  {
    "registrationNo": "MNS-18-946",
    "lastDateOfChange": "28/10/2023",
    "meterReading": 0,
    "runningDifference": null,
    "description": "6-50-R 16",
    "remarks": null
  },
  {
    "registrationNo": "MNS-18-948",
    "lastDateOfChange": "30/7/2022",
    "meterReading": 147232,
    "runningDifference": null,
    "description": "6-50-R 16",
    "remarks": null
  },
  {
    "registrationNo": "MNS-20-9002",
    "lastDateOfChange": 45629,
    "meterReading": 311904,
    "runningDifference": 7768,
    "description": "215-70-R 15",
    "remarks": null
  },
  {
    "registrationNo": "CAC-3405",
    "lastDateOfChange": 44598,
    "meterReading": 47860,
    "runningDifference": 59505,
    "description": "185 R 14 C",
    "remarks": null
  },
  {
    "registrationNo": "CAH-4895",
    "lastDateOfChange": 45179,
    "meterReading": 59855,
    "runningDifference": 11863,
    "description": "165-70 R 13 ",
    "remarks": null
  },
  {
    "registrationNo": "CAG-065",
    "lastDateOfChange": "14/08/2023",
    "meterReading": 164575,
    "runningDifference": 47725,
    "description": "215-70-R 15",
    "remarks": null
  },
  {
    "registrationNo": "CAP-491",
    "lastDateOfChange": null,
    "meterReading": null,
    "runningDifference": 44580,
    "description": "215-70-R 15",
    "remarks": null
  },
  {
    "registrationNo": "LD-1455",
    "lastDateOfChange": null,
    "meterReading": null,
    "runningDifference": null,
    "description": "215-70-R 15",
    "remarks": null
  },
  {
    "registrationNo": "CAD-487",
    "lastDateOfChange": null,
    "meterReading": null,
    "runningDifference": 6938,
    "description": "215-70-R 15",
    "remarks": null
  },
  {
    "registrationNo": "CAA-3624",
    "lastDateOfChange": "22/02/2024",
    "meterReading": 269580,
    "runningDifference": 13160,
    "description": "215-70-R 15",
    "remarks": null
  },
  {
    "registrationNo": "MNS-17-916",
    "lastDateOfChange": "28/12/2022",
    "meterReading": 169400,
    "runningDifference": 24224,
    "description": "215-70-R 15",
    "remarks": null
  },
  {
    "registrationNo": "MNS-18-9035",
    "lastDateOfChange": "16/12/2020",
    "meterReading": 69649,
    "runningDifference": 89939,
    "description": "185 R 14 C",
    "remarks": null
  },
  {
    "registrationNo": "MNS-18-937",
    "lastDateOfChange": "13/12/2021",
    "meterReading": 135080,
    "runningDifference": 43126,
    "description": "6-50-R 16",
    "remarks": null
  },
  {
    "registrationNo": "MNS-18-956",
    "lastDateOfChange": "30/10/2023",
    "meterReading": 152952,
    "runningDifference": 11201,
    "description": "6-50-R 16",
    "remarks": null
  },
  {
    "registrationNo": "MNS-18-965",
    "lastDateOfChange": 45081,
    "meterReading": 156950,
    "runningDifference": 17908,
    "description": "6-50-R 16",
    "remarks": null
  },
  {
    "registrationNo": "MNS-19-9002",
    "lastDateOfChange": "28/12/2022",
    "meterReading": 116600,
    "runningDifference": 24239,
    "description": "215-70-R 15",
    "remarks": null
  },
  {
    "registrationNo": "MNS-19-9004",
    "lastDateOfChange": 44357,
    "meterReading": 42410,
    "runningDifference": 45878,
    "description": "185 R 14 C",
    "remarks": null
  },
  {
    "registrationNo": "MNS-19-9016",
    "lastDateOfChange": 44753,
    "meterReading": 117510,
    "runningDifference": 27624,
    "description": "215-70-R 15",
    "remarks": null
  },
  {
    "registrationNo": "MNS-19-9035",
    "lastDateOfChange": 45446,
    "meterReading": 144093,
    "runningDifference": 3500,
    "description": "185 R 14 C",
    "remarks": null
  },
  {
    "registrationNo": "MNS-20-9007",
    "lastDateOfChange": "20/04/2024",
    "meterReading": 172132,
    "runningDifference": -342,
    "description": "215-70-R 15",
    "remarks": null
  },
  {
    "registrationNo": "MNS-20-9017",
    "lastDateOfChange": "18/10/2023",
    "meterReading": 205450,
    "runningDifference": 36257,
    "description": "215-70-R 15",
    "remarks": null
  },
  {
    "registrationNo": "MNS-18-952",
    "lastDateOfChange": "19/03/2024",
    "meterReading": 152700,
    "runningDifference": 760,
    "description": "6-50-R 16",
    "remarks": null
  },
  {
    "registrationNo": "CAC-3419",
    "lastDateOfChange": "14/02/2022",
    "meterReading": 39300,
    "runningDifference": 54132,
    "description": "185 R 14 C",
    "remarks": null
  },
  {
    "registrationNo": "CAA - 2833",
    "lastDateOfChange": 45267,
    "meterReading": 184379,
    "runningDifference": 34532,
    "description": "215-70-R 15",
    "remarks": null
  },
  {
    "registrationNo": "CAG-1138",
    "lastDateOfChange": "14/12/2023",
    "meterReading": 244280,
    "runningDifference": 34476,
    "description": "215-70-R 15",
    "remarks": null
  },
  {
    "registrationNo": "CAG-068",
    "lastDateOfChange": 45445,
    "meterReading": 232245,
    "runningDifference": 10806,
    "description": "215-70-R 15",
    "remarks": null
  },
  {
    "registrationNo": "CAA-4414",
    "lastDateOfChange": 44208,
    "meterReading": 57600,
    "runningDifference": 42588,
    "description": "215-70-R 15",
    "remarks": null
  },
  {
    "registrationNo": "CAP-497",
    "lastDateOfChange": "29/03/2024",
    "meterReading": 55800,
    "runningDifference": 3092,
    "description": "215-70-R 15",
    "remarks": null
  },
  {
    "registrationNo": "CAJ-6032",
    "lastDateOfChange": 45048,
    "meterReading": 42589,
    "runningDifference": null,
    "description": "175-70-R14",
    "remarks": null
  },
  {
    "registrationNo": "LD-2372",
    "lastDateOfChange": null,
    "meterReading": null,
    "runningDifference": 13506,
    "description": "215-70-R 15",
    "remarks": null
  },
  {
    "registrationNo": "MNS-18-9041",
    "lastDateOfChange": 44783,
    "meterReading": 240000,
    "runningDifference": 59735,
    "description": "215-70-R 15",
    "remarks": null
  },
  {
    "registrationNo": "MNS-18-9018",
    "lastDateOfChange": 45142,
    "meterReading": 140080,
    "runningDifference": 31170,
    "description": "185 R 14 C",
    "remarks": null
  },
  {
    "registrationNo": "MNS-18-951",
    "lastDateOfChange": "16/03/2024",
    "meterReading": 151500,
    "runningDifference": 1687,
    "description": "6-50-R 16",
    "remarks": null
  },
  {
    "registrationNo": "MNS-18-957",
    "lastDateOfChange": "30/03/2024",
    "meterReading": 260650,
    "runningDifference": 2999,
    "description": "215-70-R 15",
    "remarks": null
  },
  {
    "registrationNo": "MNS-19-9008",
    "lastDateOfChange": "14/12/2023",
    "meterReading": 112100,
    "runningDifference": 10234,
    "description": "185 R 14 C",
    "remarks": null
  },
  {
    "registrationNo": "MNS-19-902",
    "lastDateOfChange": 45267,
    "meterReading": 271650,
    "runningDifference": 52933,
    "description": "215-70-R 15",
    "remarks": null
  },
  {
    "registrationNo": "MNS-19-921",
    "lastDateOfChange": 45352,
    "meterReading": 186409,
    "runningDifference": 10925,
    "description": "215-70-R 15",
    "remarks": null
  },
  {
    "registrationNo": "MNS-20-9001",
    "lastDateOfChange": "20/10/2023",
    "meterReading": 200500,
    "runningDifference": 23137,
    "description": "215-70-R 15",
    "remarks": null
  },
  {
    "registrationNo": "MNS-20-9018",
    "lastDateOfChange": 45353,
    "meterReading": 307484,
    "runningDifference": 13910,
    "description": "215-70-R 15",
    "remarks": null
  },
  {
    "registrationNo": "CAA-4399",
    "lastDateOfChange": "29/04/2022",
    "meterReading": 48000,
    "runningDifference": 68550,
    "description": "215-70-R 15",
    "remarks": null
  },
  {
    "registrationNo": "MNS-18-9023",
    "lastDateOfChange": 45272,
    "meterReading": 232660,
    "runningDifference": 19216,
    "description": "215-70-R 15",
    "remarks": null
  },
  {
    "registrationNo": "CAD-5210",
    "lastDateOfChange": 45266,
    "meterReading": 65342,
    "runningDifference": 27550,
    "description": "215-70-R 15",
    "remarks": null
  },
  {
    "registrationNo": "CAE-5458",
    "lastDateOfChange": "16/08/2023",
    "meterReading": 123300,
    "runningDifference": 35654,
    "description": "215-70-R 15",
    "remarks": null
  },
  {
    "registrationNo": "CAE-5484",
    "lastDateOfChange": 45447,
    "meterReading": 235350,
    "runningDifference": 470,
    "description": "215-70-R 15",
    "remarks": null
  },
  {
    "registrationNo": "CAJ-8051",
    "lastDateOfChange": "24/02/2024",
    "meterReading": 147726,
    "runningDifference": 14361,
    "description": "215-70-R 15",
    "remarks": null
  },
  {
    "registrationNo": "MNS-19-9012",
    "lastDateOfChange": 45325,
    "meterReading": 202100,
    "runningDifference": 2971,
    "description": "215-70-R 15",
    "remarks": null
  },
  {
    "registrationNo": "CAK-9772",
    "lastDateOfChange": null,
    "meterReading": null,
    "runningDifference": 57786,
    "description": "215-70-R 15",
    "remarks": null
  },
  {
    "registrationNo": "CAP-3102",
    "lastDateOfChange": "24/02/2024",
    "meterReading": 20600,
    "runningDifference": 5450,
    "description": "175-70-R14 C",
    "remarks": null
  },
  {
    "registrationNo": "CH-1328",
    "lastDateOfChange": null,
    "meterReading": null,
    "runningDifference": null,
    "description": null,
    "remarks": null
  },
  {
    "registrationNo": "MNS-18-9027",
    "lastDateOfChange": 45022,
    "meterReading": 110130,
    "runningDifference": 14165,
    "description": "185 R 14 C",
    "remarks": null
  },
  {
    "registrationNo": "MNS-18-9045",
    "lastDateOfChange": 45205,
    "meterReading": 213130,
    "runningDifference": 46440,
    "description": "215-70-R 15",
    "remarks": null
  },
  {
    "registrationNo": "MNS-18-9049",
    "lastDateOfChange": 45148,
    "meterReading": 38801,
    "runningDifference": 26928,
    "description": "215-70-R 15",
    "remarks": null
  },
  {
    "registrationNo": "MNS-19-905",
    "lastDateOfChange": 45110,
    "meterReading": 192200,
    "runningDifference": 41051,
    "description": "215-70-R 15",
    "remarks": null
  },
  {
    "registrationNo": "CAA-4438",
    "lastDateOfChange": "14/09/2023",
    "meterReading": 149924,
    "runningDifference": 27460,
    "description": "215-70-R 15",
    "remarks": null
  },
  {
    "registrationNo": "CAD-6009",
    "lastDateOfChange": "27/10/2023",
    "meterReading": 75810,
    "runningDifference": 9746,
    "description": "215-70-R 15",
    "remarks": null
  },
  {
    "registrationNo": "CAF-6791",
    "lastDateOfChange": "24/03/2024",
    "meterReading": 145556,
    "runningDifference": 3998,
    "description": "215-70-R 15",
    "remarks": null
  },
  {
    "registrationNo": "CAG-1128",
    "lastDateOfChange": "18/02/2024",
    "meterReading": 239618,
    "runningDifference": 13070,
    "description": "215-70-R 15",
    "remarks": null
  },
  {
    "registrationNo": "CAP-3078",
    "lastDateOfChange": 45629,
    "meterReading": 29991,
    "runningDifference": 1853,
    "description": "175-70-R14 C",
    "remarks": null
  },
  {
    "registrationNo": "CAP-3093",
    "lastDateOfChange": null,
    "meterReading": null,
    "runningDifference": 26215,
    "description": "175-70-R14 C",
    "remarks": null
  },
  {
    "registrationNo": "MNS-20-9005",
    "lastDateOfChange": 45352,
    "meterReading": 147495,
    "runningDifference": 17153,
    "description": "215-70-R 15",
    "remarks": "04 tyre issued 16/03/2022 (96937)--02 tyre issued 21/09/2022 (114089)--02 tyre issued 15/11/2022 (118735)--02 tyre issued 27/01/2023 (123528)--04 tyre issued 14/06/2023 (133750)"
  },
  {
    "registrationNo": "CAD-896",
    "lastDateOfChange": null,
    "meterReading": null,
    "runningDifference": 6964,
    "description": "215-70-R 15",
    "remarks": null
  },
  {
    "registrationNo": "MNS-17-904",
    "lastDateOfChange": 44936,
    "meterReading": 297148,
    "runningDifference": 23642,
    "description": "215-70-R 15",
    "remarks": "04 tyre issue on 17-05-2023 (281616)"
  },
  {
    "registrationNo": "MNS-17-922",
    "lastDateOfChange": "14/08/2023",
    "meterReading": 187307,
    "runningDifference": 15163,
    "description": "6-50-R 16",
    "remarks": null
  },
  {
    "registrationNo": "MNS-18-9012",
    "lastDateOfChange": 45081,
    "meterReading": 281765,
    "runningDifference": 40296,
    "description": "215-70-R 15",
    "remarks": "04 tyre issue on 05-12-2022 (263575)--01 tyre issue on 21-01-2023 (270085)"
  },
  {
    "registrationNo": "MNS-18-929",
    "lastDateOfChange": 45507,
    "meterReading": 169641,
    "runningDifference": 1358,
    "description": "6-50-R 16",
    "remarks": null
  },
  {
    "registrationNo": "MNS-18-930",
    "lastDateOfChange": 44081,
    "meterReading": 85214,
    "runningDifference": 58415,
    "description": "6-50-R 16",
    "remarks": null
  },
  {
    "registrationNo": "MNS-18-962",
    "lastDateOfChange": 44784,
    "meterReading": 148890,
    "runningDifference": 46959,
    "description": "6-50-R 16",
    "remarks": null
  },
  {
    "registrationNo": "MNS-19-9001",
    "lastDateOfChange": 44989,
    "meterReading": 196493,
    "runningDifference": 36612,
    "description": "215-70-R 15",
    "remarks": null
  },
  {
    "registrationNo": "MNS-19-9031",
    "lastDateOfChange": 45293,
    "meterReading": 140712,
    "runningDifference": 4813,
    "description": "185 R 14 C",
    "remarks": null
  },
  {
    "registrationNo": "MNS-19-9044",
    "lastDateOfChange": 44965,
    "meterReading": 214711,
    "runningDifference": 35956,
    "description": "215-70-R 15",
    "remarks": null
  },
  {
    "registrationNo": "MNS-19-9057",
    "lastDateOfChange": "22/09/2023",
    "meterReading": 221720,
    "runningDifference": 30304,
    "description": "215-70-R 15",
    "remarks": null
  },
  {
    "registrationNo": "MNS-19-907",
    "lastDateOfChange": "15/04/2024",
    "meterReading": 275270,
    "runningDifference": 342,
    "description": "215-70-R 15",
    "remarks": null
  },
  {
    "registrationNo": "MNS-19-914",
    "lastDateOfChange": "18/12/2023",
    "meterReading": 232518,
    "runningDifference": 18322,
    "description": "215-70-R 15",
    "remarks": null
  },
  {
    "registrationNo": "CH - 0726",
    "lastDateOfChange": 44815,
    "meterReading": 94252,
    "runningDifference": 42098,
    "description": "185 R 14 C",
    "remarks": null
  },
  {
    "registrationNo": "CAF-3566",
    "lastDateOfChange": "29/7/2022",
    "meterReading": 51923,
    "runningDifference": 25600,
    "description": "185 R 14 C",
    "remarks": null
  },
  {
    "registrationNo": "CAD-6034",
    "lastDateOfChange": "23/10/2023",
    "meterReading": 78780,
    "runningDifference": 15617,
    "description": "215-70-R 15",
    "remarks": "01 tyre issue on 21-01-2023 (60493)"
  },
  {
    "registrationNo": "CAF-6785",
    "lastDateOfChange": "19/11/2023",
    "meterReading": 262734,
    "runningDifference": 47266,
    "description": "215-70-R 15",
    "remarks": null
  },
  {
    "registrationNo": "CAF-6821",
    "lastDateOfChange": "27/02/2027",
    "meterReading": 232367,
    "runningDifference": 12671,
    "description": "215-70-R 15",
    "remarks": null
  },
  {
    "registrationNo": "CAA-2840",
    "lastDateOfChange": "18/12/2023",
    "meterReading": 313468,
    "runningDifference": 17540,
    "description": "215-70-R 15",
    "remarks": null
  },
  {
    "registrationNo": "CAK-9765",
    "lastDateOfChange": 45269,
    "meterReading": 54073,
    "runningDifference": 30311,
    "description": "215-70-R 15",
    "remarks": null
  },
  {
    "registrationNo": "CAJ-6019",
    "lastDateOfChange": 45628,
    "meterReading": 64526,
    "runningDifference": 3615,
    "description": "175-70-R14",
    "remarks": "04 tyre issue on 27-04-2023 (41888)"
  },
  {
    "registrationNo": "CAN-1832",
    "lastDateOfChange": "25/03/2024",
    "meterReading": 33475,
    "runningDifference": 1358,
    "description": "175-70-R14 C",
    "remarks": null
  },
  {
    "registrationNo": "CAL-8456 ",
    "lastDateOfChange": "19/11/2023",
    "meterReading": 105899,
    "runningDifference": 51086,
    "description": "215-70-R 15",
    "remarks": null
  },
  {
    "registrationNo": "CAM-1943 ",
    "lastDateOfChange": "23/09/2023",
    "meterReading": 42743,
    "runningDifference": 42319,
    "description": "215-70-R 15",
    "remarks": null
  },
  {
    "registrationNo": "CH-1336",
    "lastDateOfChange": null,
    "meterReading": null,
    "runningDifference": 4355,
    "description": "215-70-R 15",
    "remarks": null
  },
  {
    "registrationNo": "MNS-17-912",
    "lastDateOfChange": 45355,
    "meterReading": 211419,
    "runningDifference": 481,
    "description": "6-50-R 16",
    "remarks": null
  },
  {
    "registrationNo": "MNS-17-917",
    "lastDateOfChange": 45179,
    "meterReading": 310885,
    "runningDifference": 18317,
    "description": "215-70-R 15",
    "remarks": null
  },
  {
    "registrationNo": "MNS-19-925",
    "lastDateOfChange": "27/03/2024",
    "meterReading": 321519,
    "runningDifference": 3957,
    "description": "215-70-R 15",
    "remarks": null
  },
  {
    "registrationNo": "CAC-5073",
    "lastDateOfChange": "30/08/2023",
    "meterReading": 0,
    "runningDifference": null,
    "description": "215-70-R 15",
    "remarks": null
  },
  {
    "registrationNo": "CAD-6061",
    "lastDateOfChange": "15/08/2023",
    "meterReading": 72540,
    "runningDifference": null,
    "description": "215-70-R 15",
    "remarks": null
  },
  {
    "registrationNo": "MNS-18-949",
    "lastDateOfChange": 44573,
    "meterReading": 109607,
    "runningDifference": null,
    "description": "6-50-R 16",
    "remarks": null
  },
  {
    "registrationNo": "CAM-1952",
    "lastDateOfChange": "24/02/2024",
    "meterReading": 70557,
    "runningDifference": 10644,
    "description": "215-70-R 15",
    "remarks": null
  },
  {
    "registrationNo": "CH-1455",
    "lastDateOfChange": null,
    "meterReading": null,
    "runningDifference": 1550,
    "description": "215-70-R 15",
    "remarks": null
  },
  {
    "registrationNo": "CAA-2830",
    "lastDateOfChange": "24/01/2024",
    "meterReading": 308266,
    "runningDifference": 16205,
    "description": "215-70-R 15",
    "remarks": "02 tyre issued 7/02/2023 (221632)--02 tyre issued 13-07-2023 (272837)--02 tyre issued 02-08-2023 (277982)"
  },
  {
    "registrationNo": "MNS-17-924",
    "lastDateOfChange": "18/12/2023",
    "meterReading": 325891,
    "runningDifference": 10514,
    "description": "6-50-R 16",
    "remarks": null
  },
  {
    "registrationNo": "MNS-18-9008",
    "lastDateOfChange": 44967,
    "meterReading": 324366,
    "runningDifference": 33839,
    "description": "185 R 14 C",
    "remarks": null
  },
  {
    "registrationNo": "MNS-18-931",
    "lastDateOfChange": "23/01/2023",
    "meterReading": 322616,
    "runningDifference": 60139,
    "description": "6-50-R 16",
    "remarks": null
  },
  {
    "registrationNo": "MNS-19-9015",
    "lastDateOfChange": "17/02/2024",
    "meterReading": 355824,
    "runningDifference": 11433,
    "description": "6-50-R 16",
    "remarks": "04 tyre issued 10/10/2023 (326150)"
  },
  {
    "registrationNo": "MNS-19-9025",
    "lastDateOfChange": "26/12/2023",
    "meterReading": 274320,
    "runningDifference": 8814,
    "description": "185 R 14 C",
    "remarks": "01 tyre issued 09/07/2023 (253280)--04 tyre issued 15/05/2023 (245839)"
  },
  {
    "registrationNo": "MNS-19-9026",
    "lastDateOfChange": "20/07/2023",
    "meterReading": 261047,
    "runningDifference": 41154,
    "description": "185 R 14 C",
    "remarks": null
  },
  {
    "registrationNo": "MNS-19-9052",
    "lastDateOfChange": 45117,
    "meterReading": 350700,
    "runningDifference": 48644,
    "description": "215-70-R 15",
    "remarks": "04 tyre issued 26/06/2023 (320700)"
  },
  {
    "registrationNo": "MNS-20-9021",
    "lastDateOfChange": "15/04/2024",
    "meterReading": 394488,
    "runningDifference": 5996,
    "description": "215-70-R 15",
    "remarks": "02 tyre issued 10/07/2023 (343640) --02 tyre issued 01-08-2023 (348393)--02 tyre issued 24-01-2024 (383842)"
  },
  {
    "registrationNo": "CAF-6789",
    "lastDateOfChange": 45088,
    "meterReading": 268766,
    "runningDifference": 46286,
    "description": "215-70-R 15",
    "remarks": null
  },
  {
    "registrationNo": "CAJ-8053",
    "lastDateOfChange": "30/03/2024",
    "meterReading": 262315,
    "runningDifference": 3691,
    "description": "215-70-R 15",
    "remarks": null
  },
  {
    "registrationNo": "CAP-513",
    "lastDateOfChange": "24/01/2024",
    "meterReading": 69005,
    "runningDifference": 16649,
    "description": "175-70-R14 C",
    "remarks": "01 tyre issued 23/07/2023 (31147)"
  },
  {
    "registrationNo": "CAD-456",
    "lastDateOfChange": null,
    "meterReading": null,
    "runningDifference": 17245,
    "description": "215-70-R 15",
    "remarks": null
  },
  {
    "registrationNo": "MNS-17-903",
    "lastDateOfChange": 45239,
    "meterReading": 335870,
    "runningDifference": 34650,
    "description": "215-70-R 15",
    "remarks": null
  },
  {
    "registrationNo": "MNS-18-927",
    "lastDateOfChange": 44843,
    "meterReading": 0,
    "runningDifference": 129828,
    "description": "6-50-R 16",
    "remarks": null
  },
  {
    "registrationNo": "MNS-18-935",
    "lastDateOfChange": "21/06/2023",
    "meterReading": 142853,
    "runningDifference": 23469,
    "description": "6-50-R 16",
    "remarks": null
  },
  {
    "registrationNo": "MNS-18-942",
    "lastDateOfChange": "15/10/2022",
    "meterReading": 0,
    "runningDifference": 172466,
    "description": "6-50-R 16",
    "remarks": null
  },
  {
    "registrationNo": "MNS-18-993",
    "lastDateOfChange": "19/12/2023",
    "meterReading": 371792,
    "runningDifference": 15589,
    "description": "215-70-R 15",
    "remarks": null
  },
  {
    "registrationNo": "MNS-19-9011",
    "lastDateOfChange": "20/11/2023",
    "meterReading": 306680,
    "runningDifference": 17027,
    "description": "215-70-R 15",
    "remarks": null
  },
  {
    "registrationNo": "MNS-19-9023",
    "lastDateOfChange": "22/09/2023",
    "meterReading": 105034,
    "runningDifference": 15761,
    "description": "185 R 14 C",
    "remarks": "02 tyre issued 31-07-2023 (99467)"
  },
  {
    "registrationNo": "MNS-19-9055",
    "lastDateOfChange": "15/02/2024",
    "meterReading": 299612,
    "runningDifference": 9991,
    "description": "215-70-R 15",
    "remarks": null
  },
  {
    "registrationNo": "CAG-073",
    "lastDateOfChange": "16/03/2024",
    "meterReading": 209493,
    "runningDifference": 7085,
    "description": "215-70-R 15",
    "remarks": null
  },
  {
    "registrationNo": "MNS-18-9005",
    "lastDateOfChange": "15/09/2023",
    "meterReading": 244599,
    "runningDifference": 26422,
    "description": "215-70-R 15",
    "remarks": null
  },
  {
    "registrationNo": "MNS-18-9032",
    "lastDateOfChange": "17/01/2024",
    "meterReading": 217648,
    "runningDifference": 9829,
    "description": "185 R 14 C",
    "remarks": null
  },
  {
    "registrationNo": "CAF-6811",
    "lastDateOfChange": "29/02/2024",
    "meterReading": 142603,
    "runningDifference": 8452,
    "description": "215-70-R 15",
    "remarks": null
  },
  {
    "registrationNo": "MNS-18-9028",
    "lastDateOfChange": 45629,
    "meterReading": 287770,
    "runningDifference": 6588,
    "description": "185 R 14 C",
    "remarks": null
  },
  {
    "registrationNo": "MNS-18-9048",
    "lastDateOfChange": 44967,
    "meterReading": 252200,
    "runningDifference": 31898,
    "description": "215-70-R 15",
    "remarks": null
  },
  {
    "registrationNo": "MNS-18-939",
    "lastDateOfChange": 44751,
    "meterReading": 0,
    "runningDifference": null,
    "description": "6-50-R 16",
    "remarks": null
  },
  {
    "registrationNo": "MNS-18-945",
    "lastDateOfChange": "14/10/2022",
    "meterReading": 189465,
    "runningDifference": 39825,
    "description": "6-50-R 16",
    "remarks": null
  },
  {
    "registrationNo": "MNS-19-9018",
    "lastDateOfChange": 45058,
    "meterReading": 262351,
    "runningDifference": 13041,
    "description": "215-70-R 15",
    "remarks": null
  },
  {
    "registrationNo": "MNS-19-9036",
    "lastDateOfChange": 45269,
    "meterReading": 179230,
    "runningDifference": 33002,
    "description": "185 R 14 C",
    "remarks": null
  },
  {
    "registrationNo": "CAE-5499",
    "lastDateOfChange": "25/01/2024",
    "meterReading": 168976,
    "runningDifference": 25567,
    "description": "215-70-R 15",
    "remarks": null
  },
  {
    "registrationNo": "CAN-1834",
    "lastDateOfChange": 45354,
    "meterReading": 92182,
    "runningDifference": 9440,
    "description": "175-70-R14 C",
    "remarks": null
  },
  {
    "registrationNo": "CAM-1947 ",
    "lastDateOfChange": 45209,
    "meterReading": 61705,
    "runningDifference": 41300,
    "description": "215-70-R 15",
    "remarks": null
  },
  {
    "registrationNo": "MNS-18-928",
    "lastDateOfChange": "13/01/2024",
    "meterReading": 276840,
    "runningDifference": 5731,
    "description": "6-50-R 16",
    "remarks": null
  },
  {
    "registrationNo": "MNS-18-9015",
    "lastDateOfChange": 45058,
    "meterReading": 195107,
    "runningDifference": 11356,
    "description": "185 R 14 C",
    "remarks": "04 tyre issued 14-09-2022 (153228)--02 tyre issued on 29-08-2023 (185791)"
  },
  {
    "registrationNo": "MNS-18-9038",
    "lastDateOfChange": "29/02/2024",
    "meterReading": 244042,
    "runningDifference": 5903,
    "description": "215-70-R 15",
    "remarks": null
  },
  {
    "registrationNo": "MNS-18-997",
    "lastDateOfChange": 44989,
    "meterReading": 216186,
    "runningDifference": 25655,
    "description": "215-70-R 15",
    "remarks": null
  },
  {
    "registrationNo": "MNS-19-9048",
    "lastDateOfChange": 45086,
    "meterReading": 189372,
    "runningDifference": 20554,
    "description": "215-70-R 15",
    "remarks": null
  },
  {
    "registrationNo": "MNS-19-9051",
    "lastDateOfChange": "25/08/2023",
    "meterReading": 0,
    "runningDifference": null,
    "description": "215-70-R 15",
    "remarks": "04 tyre issued 04-11-2022 (175457)--02 tyre change on 01/08/2023 (Faulty)"
  },
  {
    "registrationNo": "CAA-4393",
    "lastDateOfChange": "24/10/2023",
    "meterReading": 73020,
    "runningDifference": 17480,
    "description": "215-70-R 15",
    "remarks": null
  },
  {
    "registrationNo": "CAA-3206",
    "lastDateOfChange": 45114,
    "meterReading": 137917,
    "runningDifference": 34841,
    "description": "215-70-R 15",
    "remarks": null
  },
  {
    "registrationNo": "CAG-7229",
    "lastDateOfChange": "29/01/2024",
    "meterReading": 200600,
    "runningDifference": 22467,
    "description": "215-70-R 15",
    "remarks": "04 tyre issued 19-07-2023 (146294)--02 tyre changed on 22-11-2023 (179207)"
  },
  {
    "registrationNo": "MNS-17-919",
    "lastDateOfChange": "18/09/2023",
    "meterReading": 196813,
    "runningDifference": 43540,
    "description": "215-70-R 15",
    "remarks": null
  },
  {
    "registrationNo": "MNS-19-912",
    "lastDateOfChange": 45024,
    "meterReading": 131681,
    "runningDifference": 14217,
    "description": "215-70-R 15",
    "remarks": "04 tyre issued 23-07-2022 (102265)--04 tyre issued 19-12-2022 (115180)--01 tyre issued 06/03/2024 (143714)"
  },
  {
    "registrationNo": "CAJ-8044",
    "lastDateOfChange": 45241,
    "meterReading": 111392,
    "runningDifference": 15309,
    "description": "215-70-R 15",
    "remarks": "04 tyre changed on 01-06-2023 (83054)--01 tyre issued on 06/03/2024 (122603)"
  },
  {
    "registrationNo": "MNS-18-9021",
    "lastDateOfChange": "17/01/2024",
    "meterReading": 138770,
    "runningDifference": 9209,
    "description": "185 R 14 C",
    "remarks": "04 tyre change on 10/01/2022 (93130)"
  },
  {
    "registrationNo": "MNS-18-9039",
    "lastDateOfChange": 45269,
    "meterReading": 254148,
    "runningDifference": 39115,
    "description": "215-70-R 15",
    "remarks": null
  },
  {
    "registrationNo": "MNS-18-9043",
    "lastDateOfChange": 45294,
    "meterReading": 302263,
    "runningDifference": 6976,
    "description": "215-70-R 15",
    "remarks": null
  },
  {
    "registrationNo": "CAP-3082",
    "lastDateOfChange": "28/03/2024",
    "meterReading": 21410,
    "runningDifference": 1120,
    "description": "175-70-R14 C",
    "remarks": null
  },
  {
    "registrationNo": "MNS-18-9011",
    "lastDateOfChange": 45209,
    "meterReading": 416862,
    "runningDifference": 36181,
    "description": "215-70-R 15",
    "remarks": "01 Tyre as a stepny 17-06-2023 (400953)"
  },
  {
    "registrationNo": "MNS-18-9036",
    "lastDateOfChange": 44808,
    "meterReading": 58745,
    "runningDifference": 49784,
    "description": "185 R 14 C",
    "remarks": null
  },
  {
    "registrationNo": "MNS-19-9007",
    "lastDateOfChange": 44838,
    "meterReading": 69906,
    "runningDifference": 49722,
    "description": "185 R 14 C",
    "remarks": null
  },
  {
    "registrationNo": "MNS-19-9039",
    "lastDateOfChange": "21/06/2021",
    "meterReading": 52260,
    "runningDifference": 41190,
    "description": "185 R 14 C",
    "remarks": null
  },
  {
    "registrationNo": "MNS-19-9043",
    "lastDateOfChange": 45355,
    "meterReading": 321214,
    "runningDifference": 1027,
    "description": "215-70-R 15",
    "remarks": null
  },
  {
    "registrationNo": "CAA-4448",
    "lastDateOfChange": "15/06/2023",
    "meterReading": 225565,
    "runningDifference": 41222,
    "description": "215-70-R 15",
    "remarks": null
  },
  {
    "registrationNo": "CAG-1131",
    "lastDateOfChange": 45028,
    "meterReading": 221367,
    "runningDifference": 52327,
    "description": "215-70-R 15",
    "remarks": null
  },
  {
    "registrationNo": "CAG-069",
    "lastDateOfChange": "17/12/2023",
    "meterReading": 236395,
    "runningDifference": 47473,
    "description": "215-70-R 15",
    "remarks": "01 Tyre as a stepny 17-06-2023 (186650)"
  },
  {
    "registrationNo": "CAG-1133",
    "lastDateOfChange": "14/01/2024",
    "meterReading": 230750,
    "runningDifference": 24577,
    "description": "215-70-R 15",
    "remarks": null
  },
  {
    "registrationNo": "CAD-6047",
    "lastDateOfChange": "28/03/2024",
    "meterReading": 106109,
    "runningDifference": 2441,
    "description": "215-70-R 15",
    "remarks": null
  },
  {
    "registrationNo": "CAA - 2781",
    "lastDateOfChange": 45028,
    "meterReading": 133717,
    "runningDifference": 35096,
    "description": "215-70-R 15",
    "remarks": "01 Tyre as a stepny 11-10-2022 (96458)"
  },
  {
    "registrationNo": "CAJ-8050",
    "lastDateOfChange": 45148,
    "meterReading": 127442,
    "runningDifference": 55414,
    "description": "215-70-R 15",
    "remarks": "01 Spare Tyre issued MR 154900  08-01-2024"
  },
  {
    "registrationNo": "CAA-2798",
    "lastDateOfChange": "18/10/2023",
    "meterReading": 253655,
    "runningDifference": 35843,
    "description": "215-70-R 15",
    "remarks": null
  },
  {
    "registrationNo": "MNS-18-9020",
    "lastDateOfChange": "28/03/2024",
    "meterReading": 165800,
    "runningDifference": 671,
    "description": "185 R 14 C",
    "remarks": null
  },
  {
    "registrationNo": "MNS-19-901",
    "lastDateOfChange": 45415,
    "meterReading": 364616,
    "runningDifference": 7559,
    "description": "215-70-R 15",
    "remarks": null
  },
  {
    "registrationNo": "MNS-18-959",
    "lastDateOfChange": "22/09/2023",
    "meterReading": 311683,
    "runningDifference": 27028,
    "description": "215-70-R 15",
    "remarks": null
  },
  {
    "registrationNo": "BD-8538",
    "lastDateOfChange": "16/06/2023",
    "meterReading": 0,
    "runningDifference": null,
    "description": "235/70 R 15",
    "remarks": null
  },
  {
    "registrationNo": "CAP-493",
    "lastDateOfChange": "14/04/2024",
    "meterReading": 50447,
    "runningDifference": -692,
    "description": "215-70-R 15",
    "remarks": null
  },
  {
    "registrationNo": "MNS-19-909",
    "lastDateOfChange": "18/09/2023",
    "meterReading": 136658,
    "runningDifference": 23028,
    "description": "215-70-R 15",
    "remarks": "04 tyre issued on 05/02/2023 (116781) "
  },
  {
    "registrationNo": "MNS-18-9017",
    "lastDateOfChange": 45235,
    "meterReading": 217072,
    "runningDifference": 46504,
    "description": "185 R 14 C",
    "remarks": null
  },
  {
    "registrationNo": "MNS-18-960",
    "lastDateOfChange": "16/08/2023",
    "meterReading": 291099,
    "runningDifference": 42588,
    "description": "215-70-R 15",
    "remarks": null
  },
  {
    "registrationNo": "MNS-19-9058",
    "lastDateOfChange": 45353,
    "meterReading": 242320,
    "runningDifference": 11294,
    "description": "215-70-R 15",
    "remarks": null
  },
  {
    "registrationNo": "MNS-18-947",
    "lastDateOfChange": 45052,
    "meterReading": 157177,
    "runningDifference": 28632,
    "description": "6-50-R 16",
    "remarks": null
  },
  {
    "registrationNo": "MNS-19-9053",
    "lastDateOfChange": "30/03/2024",
    "meterReading": 261616,
    "runningDifference": 2836,
    "description": "215-70-R 15",
    "remarks": null
  },
  {
    "registrationNo": "MNS-17-909",
    "lastDateOfChange": "18/02/2024",
    "meterReading": 264395,
    "runningDifference": 9952,
    "description": "215-70-R 15",
    "remarks": null
  },
  {
    "registrationNo": "CH-1454",
    "lastDateOfChange": null,
    "meterReading": null,
    "runningDifference": 823,
    "description": "215-70-R 15",
    "remarks": null
  },
  {
    "registrationNo": "CAA - 2806",
    "lastDateOfChange": "20/03/2024",
    "meterReading": 274275,
    "runningDifference": 5570,
    "description": "215-70-R 15",
    "remarks": null
  },
  {
    "registrationNo": "MNS-18-943",
    "lastDateOfChange": 45445,
    "meterReading": 249707,
    "runningDifference": 10657,
    "description": "6-50-R 16",
    "remarks": null
  },
  {
    "registrationNo": "CAC-3428",
    "lastDateOfChange": 44661,
    "meterReading": 109983,
    "runningDifference": 60385,
    "description": "195 R 14 C",
    "remarks": null
  },
  {
    "registrationNo": "CAK-9763",
    "lastDateOfChange": "18/02/2024",
    "meterReading": 107018,
    "runningDifference": 11208,
    "description": "215-70-R 15",
    "remarks": null
  },
  {
    "registrationNo": "CAD-5994",
    "lastDateOfChange": 45386,
    "meterReading": 157907,
    "runningDifference": -4288,
    "description": "215-70-R 15",
    "remarks": null
  },
  {
    "registrationNo": "CAD-6016",
    "lastDateOfChange": 45239,
    "meterReading": 138320,
    "runningDifference": 33587,
    "description": "215-70-R 15",
    "remarks": null
  },
  {
    "registrationNo": "MNS-19-9019",
    "lastDateOfChange": "13/01/2024",
    "meterReading": 0,
    "runningDifference": null,
    "description": "215-70-R 15",
    "remarks": null
  },
  {
    "registrationNo": "MNS-19-903",
    "lastDateOfChange": "21/02/2024",
    "meterReading": 395189,
    "runningDifference": 12664,
    "description": "215-70-R 15",
    "remarks": null
  },
  {
    "registrationNo": "MNS-19-9040",
    "lastDateOfChange": "19/12/2023",
    "meterReading": 178381,
    "runningDifference": 20208,
    "description": "185 R 14 C",
    "remarks": null
  },
  {
    "registrationNo": "MNS-19-924",
    "lastDateOfChange": "20/12/2023",
    "meterReading": "Nil",
    "runningDifference": null,
    "description": "215-70-R 15",
    "remarks": null
  },
  {
    "registrationNo": "CAF-3559 ",
    "lastDateOfChange": 44713,
    "meterReading": 40035,
    "runningDifference": 26333,
    "description": "185 R 14 C",
    "remarks": null
  },
  {
    "registrationNo": "CAD-5237",
    "lastDateOfChange": "19/10/2023",
    "meterReading": 160311,
    "runningDifference": 32023,
    "description": "215-70-R 15",
    "remarks": null
  },
  {
    "registrationNo": "CAD-6063",
    "lastDateOfChange": "13/07/2023",
    "meterReading": 135126,
    "runningDifference": 42326,
    "description": "215-70-R 15",
    "remarks": null
  },
  {
    "registrationNo": "CAJ-5586",
    "lastDateOfChange": "20/06/2023",
    "meterReading": 51342,
    "runningDifference": 22725,
    "description": "165-70 R 13",
    "remarks": null
  },
  {
    "registrationNo": "CAM-1913 ",
    "lastDateOfChange": "25/03/2024",
    "meterReading": 108976,
    "runningDifference": 7730,
    "description": "215-70-R 15",
    "remarks": null
  },
  {
    "registrationNo": "MNS-17-915",
    "lastDateOfChange": 44994,
    "meterReading": 329520,
    "runningDifference": 33576,
    "description": "215-70-R 15",
    "remarks": null
  },
  {
    "registrationNo": "MNS-18-940",
    "lastDateOfChange": "29/05/2023",
    "meterReading": 166777,
    "runningDifference": 13210,
    "description": "6-50-R 16",
    "remarks": null
  },
  {
    "registrationNo": "MNS-19-9028",
    "lastDateOfChange": 45325,
    "meterReading": 168223,
    "runningDifference": 3334,
    "description": "185 R 14 C",
    "remarks": null
  },
  {
    "registrationNo": "MNS-19-9046",
    "lastDateOfChange": 45148,
    "meterReading": 246835,
    "runningDifference": 42181,
    "description": "215-70-R 15",
    "remarks": null
  },
  {
    "registrationNo": "MNS-19-922",
    "lastDateOfChange": 45241,
    "meterReading": 355382,
    "runningDifference": 34063,
    "description": "215-70-R 15",
    "remarks": null
  },
  {
    "registrationNo": "CAD-5213",
    "lastDateOfChange": "28/02/2024",
    "meterReading": 190737,
    "runningDifference": 9457,
    "description": "215-70-R 15",
    "remarks": null
  },
  {
    "registrationNo": "CAA-2802",
    "lastDateOfChange": 45149,
    "meterReading": 255951,
    "runningDifference": 52449,
    "description": "215-70-R 15",
    "remarks": null
  },
  {
    "registrationNo": "MNS-18-941",
    "lastDateOfChange": "15/04/2024",
    "meterReading": 0,
    "runningDifference": null,
    "description": "6-50-R 16",
    "remarks": null
  },
  {
    "registrationNo": "MNS-19-906",
    "lastDateOfChange": "29/02/2024",
    "meterReading": 380292,
    "runningDifference": 18606,
    "description": "215-70-R 15",
    "remarks": null
  },
  {
    "registrationNo": "MNS-20-9006",
    "lastDateOfChange": 45028,
    "meterReading": 350759,
    "runningDifference": 41576,
    "description": "215-70-R 15",
    "remarks": null
  },
  {
    "registrationNo": "CAD-5216",
    "lastDateOfChange": 45566,
    "meterReading": 176978,
    "runningDifference": 13822,
    "description": "215-70-R 15",
    "remarks": null
  },
  {
    "registrationNo": "CAN-1851",
    "lastDateOfChange": "19/09/2023",
    "meterReading": 43390,
    "runningDifference": 30851,
    "description": "175-70-R14 C",
    "remarks": null
  },
  {
    "registrationNo": "CAP-498",
    "lastDateOfChange": 45629,
    "meterReading": 69511,
    "runningDifference": 4455,
    "description": "215-70-R 15",
    "remarks": null
  },
  {
    "registrationNo": "MNS-18-9004",
    "lastDateOfChange": "24/01/2024",
    "meterReading": 425189,
    "runningDifference": 18875,
    "description": "215-70-R 15",
    "remarks": null
  },
  {
    "registrationNo": "CAF-6787",
    "lastDateOfChange": 45568,
    "meterReading": 256830,
    "runningDifference": 8152,
    "description": "215-70-R 15",
    "remarks": "04 tyre change on 03/05/2023 (178428)--02 tyre change on 24/08/2023 (209267)--02 tyre change on 30/08/2024 (210326)"
  },
  {
    "registrationNo": "CAP-506",
    "lastDateOfChange": "26/03/2024",
    "meterReading": 67496,
    "runningDifference": 2956,
    "description": "175-70-R14 C",
    "remarks": "04 tyre change on 11/09/2023 (35723)"
  },
  {
    "registrationNo": "MNS-18-933",
    "lastDateOfChange": "20/01/2024",
    "meterReading": 273474,
    "runningDifference": 7290,
    "description": "6-50-R 16",
    "remarks": "04 tyres change on  01-08-2022 (198091)"
  },
  {
    "registrationNo": "MNS-18-936",
    "lastDateOfChange": "22/10/2023",
    "meterReading": 315990,
    "runningDifference": 27359,
    "description": "6-50-R 16",
    "remarks": null
  },
  {
    "registrationNo": "MNS-18-9022",
    "lastDateOfChange": 45241,
    "meterReading": 293561,
    "runningDifference": 30795,
    "description": "215-70-R 15",
    "remarks": "01 tyres change  on  03-01-2023 (252650)--01 tyres change  on  12-02-2023 (260078)--02 tyres issued on 23-10-2023 (290511)"
  },
  {
    "registrationNo": "CAL-8463 ",
    "lastDateOfChange": 45054,
    "meterReading": 48350,
    "runningDifference": 34330,
    "description": "215-70-R 15",
    "remarks": "01 Tyre change on 08-06-2023 MR (36527)"
  },
  {
    "registrationNo": "MNS-19-910",
    "lastDateOfChange": "15/09/2022",
    "meterReading": 56175,
    "runningDifference": 31533,
    "description": "215-70-R 15",
    "remarks": null
  },
  {
    "registrationNo": "CAC-5072",
    "lastDateOfChange": "30/05/2023",
    "meterReading": 127282,
    "runningDifference": null,
    "description": "215-70-R 15",
    "remarks": null
  },
  {
    "registrationNo": "CAJ-6021",
    "lastDateOfChange": "15/09/2023",
    "meterReading": 66372,
    "runningDifference": 20456,
    "description": "175-70-R14",
    "remarks": null
  },
  {
    "registrationNo": "MNS-18-953",
    "lastDateOfChange": "22/02/2023",
    "meterReading": 158432,
    "runningDifference": 37607,
    "description": "6-50-R 16",
    "remarks": null
  },
  {
    "registrationNo": "MNS-19-904",
    "lastDateOfChange": 45240,
    "meterReading": 295532,
    "runningDifference": 31843,
    "description": "215-70-R 15",
    "remarks": null
  },
  {
    "registrationNo": "CAP-3079",
    "lastDateOfChange": null,
    "meterReading": null,
    "runningDifference": 38935,
    "description": "175-70-R14 C",
    "remarks": "01 Tyre issued on 31-10-2023  M-15050"
  },
  {
    "registrationNo": "CAD-270",
    "lastDateOfChange": null,
    "meterReading": null,
    "runningDifference": 6769,
    "description": "215-70-R15",
    "remarks": null
  },
  {
    "registrationNo": "MNS-18-9010",
    "lastDateOfChange": 45052,
    "meterReading": 178134,
    "runningDifference": 30792,
    "description": "215-70-R 15",
    "remarks": null
  },
  {
    "registrationNo": "MNS-19-9021",
    "lastDateOfChange": 45325,
    "meterReading": 176240,
    "runningDifference": 4325,
    "description": "185 R 14 C",
    "remarks": null
  },
  {
    "registrationNo": "MNS-20-9016",
    "lastDateOfChange": "14/11/2023",
    "meterReading": 209320,
    "runningDifference": 27925,
    "description": "215-70-R 15",
    "remarks": null
  },
  {
    "registrationNo": "CAA-4423",
    "lastDateOfChange": 45325,
    "meterReading": 93478,
    "runningDifference": 4631,
    "description": "215-70-R 15",
    "remarks": "04 TYRE ISSUED ON 02-02-2023 (79768)--01 tyre issued on 29-08-2023 (Faulty)--02 tyreissued on 26-07-2023 (Faulty)"
  },
  {
    "registrationNo": "CAJ-6001",
    "lastDateOfChange": 45352,
    "meterReading": 56675,
    "runningDifference": 6750,
    "description": "175-70-R14",
    "remarks": "01 TYRE ISSUED ON 01-08-2023 (46815)"
  },
  {
    "registrationNo": "CAC-5070",
    "lastDateOfChange": "20/07/2023",
    "meterReading": 65374,
    "runningDifference": 6055,
    "description": "215-70-R 15",
    "remarks": null
  },
  {
    "registrationNo": "MNS-19-9010",
    "lastDateOfChange": 45272,
    "meterReading": 278081,
    "runningDifference": 20344,
    "description": "215-70-R 15",
    "remarks": null
  },
  {
    "registrationNo": "MNS-19-9022",
    "lastDateOfChange": "24/01/2024",
    "meterReading": 260446,
    "runningDifference": 12810,
    "description": "185 R 14 C",
    "remarks": null
  },
  {
    "registrationNo": "MNS-19-9030",
    "lastDateOfChange": "21/02/2024",
    "meterReading": 257719,
    "runningDifference": 9017,
    "description": "185 R 14 C",
    "remarks": null
  },
  {
    "registrationNo": "CAD-6023",
    "lastDateOfChange": "30/08/2023",
    "meterReading": 128869,
    "runningDifference": 40056,
    "description": "215-70-R 15",
    "remarks": "02 tyre issued on 22-01-2023 (99087)--02 tyre issued on 06/05/2023 (112955)"
  },
  {
    "registrationNo": "CAJ-6042",
    "lastDateOfChange": "19/02/2024",
    "meterReading": 85549,
    "runningDifference": 6114,
    "description": "175-70-R14",
    "remarks": "04 tyre issued on 12/09/2023 (67018)"
  },
  {
    "registrationNo": "CAL-8459 ",
    "lastDateOfChange": 45415,
    "meterReading": 87811,
    "runningDifference": 6794,
    "description": "215-70-R 15",
    "remarks": null
  },
  {
    "registrationNo": "MNS-19-9024",
    "lastDateOfChange": 45476,
    "meterReading": 149194,
    "runningDifference": 1978,
    "description": "185 R 14 C",
    "remarks": "04 tyre issued 18/04/2021 (71169)--02 tyre issued on 02/08/2023 (130210)"
  },
  {
    "registrationNo": "MNS-19-9032",
    "lastDateOfChange": 45209,
    "meterReading": 237975,
    "runningDifference": 32476,
    "description": "185 R 14 C",
    "remarks": "01 tyre issued on 25/09/2023 (235845)--01 tyre issued on 08/10/2023 (237740)"
  },
  {
    "registrationNo": "MNS-19-911",
    "lastDateOfChange": 45598,
    "meterReading": 367681,
    "runningDifference": 13639,
    "description": "215-70-R 15",
    "remarks": "04 tyre issued on 27/04/2023 (306790)--02 tyre issued on 01/08/2023 (328176)--02  tyre isued on 17-09-20223 (336816)"
  },
  {
    "registrationNo": "CAF-6812",
    "lastDateOfChange": 45568,
    "meterReading": 203842,
    "runningDifference": 7558,
    "description": "215-70-R 15",
    "remarks": "01 tyre issued on 12/12/2023 (185387)"
  },
  {
    "registrationNo": "CAC-3416",
    "lastDateOfChange": "23/07/2023",
    "meterReading": 119805,
    "runningDifference": 35707,
    "description": "185 R 14 C",
    "remarks": null
  },
  {
    "registrationNo": "CAD-656",
    "lastDateOfChange": null,
    "meterReading": null,
    "runningDifference": 13596,
    "description": "215-70-R 15",
    "remarks": null
  },
  {
    "registrationNo": "CH-1456",
    "lastDateOfChange": null,
    "meterReading": null,
    "runningDifference": 0,
    "description": "215-70-R 15",
    "remarks": null
  },
  {
    "registrationNo": "MNS-19-9038",
    "lastDateOfChange": "13/11/2023",
    "meterReading": 182575,
    "runningDifference": 20162,
    "description": "185 R 14 C",
    "remarks": null
  },
  {
    "registrationNo": "MNS-18-9019",
    "lastDateOfChange": 45507,
    "meterReading": 258915,
    "runningDifference": 3030,
    "description": "185 R 14 C",
    "remarks": "02 tyre change on 04-11-2022 (203001)--02 tyre change on 27-04-2023 (225260)--02 tyre change on 17/11/2023 (246912)"
  },
  {
    "registrationNo": "MNS-19-9047",
    "lastDateOfChange": "22/03/2024",
    "meterReading": 327324,
    "runningDifference": 4196,
    "description": "215-70-R 15",
    "remarks": null
  },
  {
    "registrationNo": "MNS-18-964",
    "lastDateOfChange": "30/05/2023",
    "meterReading": 116370,
    "runningDifference": 44855,
    "description": "6-50-R 16",
    "remarks": null
  },
  {
    "registrationNo": "CAE-5481",
    "lastDateOfChange": "30/01/2024",
    "meterReading": 201742,
    "runningDifference": 15183,
    "description": "215-70-R 15",
    "remarks": null
  },
  {
    "registrationNo": "MNS-19-9054",
    "lastDateOfChange": "21/11/2023",
    "meterReading": 210455,
    "runningDifference": 27995,
    "description": "215-70-R 15",
    "remarks": "04 tyre change on 11-03-2023 (187924)"
  },
  {
    "registrationNo": "CAD-464",
    "lastDateOfChange": null,
    "meterReading": null,
    "runningDifference": 13060,
    "description": "215-70-R 15",
    "remarks": null
  },
  {
    "registrationNo": "MNS-20-9003",
    "lastDateOfChange": "20/06/2023",
    "meterReading": 146148,
    "runningDifference": 32319,
    "description": "215-70-R 15",
    "remarks": null
  },
  {
    "registrationNo": "BC-9133",
    "lastDateOfChange": 45108,
    "meterReading": 0,
    "runningDifference": null,
    "description": "245-70 R 16",
    "remarks": null
  },
  {
    "registrationNo": "MNS-18-9051",
    "lastDateOfChange": "26/01/2024",
    "meterReading": 307462,
    "runningDifference": 17774,
    "description": "215-70-R 15",
    "remarks": null
  },
  {
    "registrationNo": "MNS-17-906",
    "lastDateOfChange": "16/10/2023",
    "meterReading": 0,
    "runningDifference": null,
    "description": "215-70-R 15",
    "remarks": null
  },
  {
    "registrationNo": "MNS-17-926",
    "lastDateOfChange": "06/06/2022",
    "meterReading": 113763,
    "runningDifference": null,
    "description": "6-50-R 16",
    "remarks": null
  },
  {
    "registrationNo": "MNS-20-9014",
    "lastDateOfChange": 44965,
    "meterReading": 125762,
    "runningDifference": 29655,
    "description": "215-70-R 15",
    "remarks": null
  },
  {
    "registrationNo": "CAN-1837",
    "lastDateOfChange": "22/08/2023",
    "meterReading": 35938,
    "runningDifference": 22079,
    "description": "175-70-R14 C",
    "remarks": null
  },
  {
    "registrationNo": "CAP-3085",
    "lastDateOfChange": null,
    "meterReading": null,
    "runningDifference": 24502,
    "description": "175-70-R14 C",
    "remarks": null
  },
  {
    "registrationNo": "MNS-18-9013",
    "lastDateOfChange": 45538,
    "meterReading": 266760,
    "runningDifference": 5003,
    "description": "215-70-R 15",
    "remarks": null
  },
  {
    "registrationNo": "MNS-18-9016",
    "lastDateOfChange": "30/01/2024",
    "meterReading": 231650,
    "runningDifference": 10120,
    "description": "185 R 14 C",
    "remarks": null
  },
  {
    "registrationNo": "CAJ-6046",
    "lastDateOfChange": "13/11/2023",
    "meterReading": 0,
    "runningDifference": null,
    "description": "175-70-R14",
    "remarks": null
  },
  {
    "registrationNo": "MNS-20-9019",
    "lastDateOfChange": 45386,
    "meterReading": 296420,
    "runningDifference": 2034,
    "description": "215-70-R 15",
    "remarks": null
  },
  {
    "registrationNo": "CAD-6012",
    "lastDateOfChange": 44993,
    "meterReading": 128564,
    "runningDifference": 34391,
    "description": "215-70-R 15",
    "remarks": "04 TYRE ISSUED ON 17-11-2023 (92155)--02 TYRE ISSUED ON 26-07-2023 (127923)"
  },
  {
    "registrationNo": "CAF-6804 ",
    "lastDateOfChange": "17/12/2023",
    "meterReading": 137465,
    "runningDifference": 22402,
    "description": "215-70-R 15",
    "remarks": null
  },
  {
    "registrationNo": "CAF-6819 ",
    "lastDateOfChange": "20/02/2024",
    "meterReading": 159260,
    "runningDifference": 8620,
    "description": "215-70-R 15",
    "remarks": null
  },
  {
    "registrationNo": "CAG-7218 ",
    "lastDateOfChange": 44965,
    "meterReading": 85893,
    "runningDifference": 30958,
    "description": "215-70-R 15",
    "remarks": null
  },
  {
    "registrationNo": "CAG-7235",
    "lastDateOfChange": "21/10/2023",
    "meterReading": 112258,
    "runningDifference": 32776,
    "description": "215-70-R 15",
    "remarks": null
  },
  {
    "registrationNo": "CAL-8454",
    "lastDateOfChange": "13/07/2023",
    "meterReading": 38216,
    "runningDifference": 42356,
    "description": "215-70-R 15",
    "remarks": null
  },
  {
    "registrationNo": "CAG-7239 ",
    "lastDateOfChange": 45149,
    "meterReading": 124385,
    "runningDifference": 28531,
    "description": "215-70-R 15",
    "remarks": null
  },
  {
    "registrationNo": "CAM-1951 ",
    "lastDateOfChange": 44994,
    "meterReading": 40241,
    "runningDifference": 38834,
    "description": "215-70-R 15",
    "remarks": null
  },
  {
    "registrationNo": "MNS-20-9012",
    "lastDateOfChange": "30/08/2023",
    "meterReading": 225007,
    "runningDifference": 35417,
    "description": "215-70-R 15",
    "remarks": null
  },
  {
    "registrationNo": "CAD-5205",
    "lastDateOfChange": "28/03/2024",
    "meterReading": 154360,
    "runningDifference": 2703,
    "description": "215-70-R 15",
    "remarks": null
  },
  {
    "registrationNo": "MNS-20-9011",
    "lastDateOfChange": 45148,
    "meterReading": 197230,
    "runningDifference": 27974,
    "description": "215-70-R 15",
    "remarks": null
  },
  {
    "registrationNo": "CAD-6006",
    "lastDateOfChange": 45293,
    "meterReading": 194163,
    "runningDifference": 8968,
    "description": "215-70-R 15",
    "remarks": null
  },
  {
    "registrationNo": "MNS-18-934",
    "lastDateOfChange": 45599,
    "meterReading": 184860,
    "runningDifference": 3568,
    "description": "6-50-R 16",
    "remarks": null
  },
  {
    "registrationNo": "CAP-509",
    "lastDateOfChange": "30/08/2023",
    "meterReading": 24293,
    "runningDifference": 27801,
    "description": "175-70-R14 C",
    "remarks": null
  },
  {
    "registrationNo": "MNS-18-944",
    "lastDateOfChange": "14/02/2021",
    "meterReading": 90165,
    "runningDifference": 50627,
    "description": "6-50-R 16",
    "remarks": null
  },
  {
    "registrationNo": "CAA - 2826",
    "lastDateOfChange": 45566,
    "meterReading": 0,
    "runningDifference": null,
    "description": "215-70-R 15",
    "remarks": null
  },
  {
    "registrationNo": "CAG-1125",
    "lastDateOfChange": "25/08/2023",
    "meterReading": 99200,
    "runningDifference": 26950,
    "description": "215-70-R 15",
    "remarks": "04 tyre change on 18/07/2022 MR (47392)--02 tyre change on 06/01/2023 MR (69560)"
  },
  {
    "registrationNo": "CAA - 2825",
    "lastDateOfChange": 45143,
    "meterReading": 124300,
    "runningDifference": 33747,
    "description": "215-70-R 15",
    "remarks": "01 tyre change on 14/04/2023 MR (122300)"
  },
  {
    "registrationNo": "CAG-1140",
    "lastDateOfChange": "20/03/2024",
    "meterReading": 138802,
    "runningDifference": 4486,
    "description": "215-70-R 15",
    "remarks": "04 tyre issued 24/01/2023 (73838)--02 tyre issued 19/06/2023 (96689)--02 tyre issued 04/07/2023 (99293)--02 tyre issued 15/08/2023 (104073)--02 tyre issued 11/11/2023 (117464)"
  },
  {
    "registrationNo": "CAA - 2810",
    "lastDateOfChange": "30/01/2024",
    "meterReading": 190945,
    "runningDifference": 12199,
    "description": "215-70-R 15",
    "remarks": "04 tyre issued 07/11/2022 (123060)--02 tyre issued 20/02/2023 (140536)--04 tyre isued on 11/05/2023 (152379)--01 tyre issued on 07/11/2023 (178946)--02 tyre issued on 31/08/2024(168682)"
  },
  {
    "registrationNo": "MNS-19-9029",
    "lastDateOfChange": 45272,
    "meterReading": 136127,
    "runningDifference": 16426,
    "description": "185 R 14 C",
    "remarks": null
  },
  {
    "registrationNo": "CAA-3751",
    "lastDateOfChange": "22/11/2023",
    "meterReading": 272798,
    "runningDifference": 25482,
    "description": "215-70-R 15",
    "remarks": null
  },
  {
    "registrationNo": "MNS-18-9029",
    "lastDateOfChange": "21/08/2023",
    "meterReading": 213090,
    "runningDifference": 32128,
    "description": "185 R 14 C",
    "remarks": null
  },
  {
    "registrationNo": "MNS-17-925",
    "lastDateOfChange": "19/06/2023",
    "meterReading": 141707,
    "runningDifference": 30297,
    "description": "6-50-R 16",
    "remarks": null
  },
  {
    "registrationNo": "CAA - 3621",
    "lastDateOfChange": 45086,
    "meterReading": 185597,
    "runningDifference": 33697,
    "description": "215-70-R 15",
    "remarks": null
  },
  {
    "registrationNo": "CAD-6029",
    "lastDateOfChange": "19/10/2023",
    "meterReading": 128376,
    "runningDifference": 25344,
    "description": "215-70-R 15",
    "remarks": null
  },
  {
    "registrationNo": "BH-2819",
    "lastDateOfChange": "25/04/2023",
    "meterReading": 0,
    "runningDifference": 40437,
    "description": "235-85-R 16",
    "remarks": "04 tyre change on 21/11/2021 MR U/S"
  },
  {
    "registrationNo": "CAA - 3232",
    "lastDateOfChange": 45236,
    "meterReading": 123991,
    "runningDifference": 38597,
    "description": "215-70-R 15",
    "remarks": null
  },
  {
    "registrationNo": "CAA - 3194",
    "lastDateOfChange": "30/12/2023",
    "meterReading": 142353,
    "runningDifference": 13321,
    "description": "215-70-R 15",
    "remarks": null
  },
  {
    "registrationNo": "MNS-20-9022",
    "lastDateOfChange": "28/11/2023",
    "meterReading": 95300,
    "runningDifference": 10119,
    "description": "215-70-R 15",
    "remarks": "02 Tyre change on 09/02/2022 (54887)--02 Tyre change on 23/01/2023 (78340)"
  },
  {
    "registrationNo": "CAA - 3190",
    "lastDateOfChange": 45323,
    "meterReading": 189458,
    "runningDifference": 17332,
    "description": "215-70-R 15",
    "remarks": "04 tyre issued on 12-03-2023 (139964)--02 tyre issued on 21-09-2023 (169647)"
  },
  {
    "registrationNo": "CAF-6779",
    "lastDateOfChange": "19/11/2023",
    "meterReading": 174922,
    "runningDifference": 35068,
    "description": "215-70-R 15",
    "remarks": null
  },
  {
    "registrationNo": "CAA - 3192",
    "lastDateOfChange": 45026,
    "meterReading": 168125,
    "runningDifference": 30329,
    "description": "215-70-R 15",
    "remarks": "04 tyre issued on 24-07-2023 (155274)"
  },
  {
    "registrationNo": "CAA-4430",
    "lastDateOfChange": 45597,
    "meterReading": 178200,
    "runningDifference": 20728,
    "description": "215-70-R 15",
    "remarks": null
  },
  {
    "registrationNo": "CAG-7220",
    "lastDateOfChange": "25/07/2023",
    "meterReading": 74895,
    "runningDifference": 31568,
    "description": "215-70-R 15",
    "remarks": null
  },
  {
    "registrationNo": "CAG-7217",
    "lastDateOfChange": 45147,
    "meterReading": 78411,
    "runningDifference": 24234,
    "description": "215-70-R 15",
    "remarks": null
  },
  {
    "registrationNo": "MNS-19-9006",
    "lastDateOfChange": "15/03/2024",
    "meterReading": 122299,
    "runningDifference": 1236,
    "description": "185 R 14 C",
    "remarks": "04 tyre changed on 17-03-2023 (90543)--02 tyre changed on 21-10-2023(110896)"
  },
  {
    "registrationNo": "CAJ-8042",
    "lastDateOfChange": "26/01/2024",
    "meterReading": 158872,
    "runningDifference": 21411,
    "description": "215-70-R 15",
    "remarks": "04 tyre changed on 15-03-2023 (47408)--04 tyre changed on 25-08-2023 (96528)--04 tyre changed on 21-10-2023 (123207)"
  },
  {
    "registrationNo": "CAJ-6008",
    "lastDateOfChange": "22/02/2024",
    "meterReading": 138888,
    "runningDifference": 11925,
    "description": "175-70-R14",
    "remarks": "04 tyre change on 13/06/2023 (84900)--04 tyre change on 12/09/2023 (101546)"
  },
  {
    "registrationNo": "CAJ-6027",
    "lastDateOfChange": "25/03/2024",
    "meterReading": 107520,
    "runningDifference": 3802,
    "description": "175-70-R14",
    "remarks": "04 tyre change dated 14/02/2023 (51186)--04 tyre change on 19/09/2023 (79335)"
  },
  {
    "registrationNo": "CAG-7224",
    "lastDateOfChange": 45272,
    "meterReading": 109997,
    "runningDifference": 25768,
    "description": "215-70-R 15",
    "remarks": "01 Tyre as a stepny MR 64555 26-01-2023"
  },
  {
    "registrationNo": "CAP-451",
    "lastDateOfChange": 45538,
    "meterReading": 47662,
    "runningDifference": 5120,
    "description": "215-70-R 15",
    "remarks": null
  },
  {
    "registrationNo": "BE-672",
    "lastDateOfChange": "26/06/2021",
    "meterReading": 220246,
    "runningDifference": 30986,
    "description": "235/70 R 15",
    "remarks": null
  },
  {
    "registrationNo": "LD-1459",
    "lastDateOfChange": null,
    "meterReading": null,
    "runningDifference": 29715,
    "description": "215-70-R 15",
    "remarks": null
  },
  {
    "registrationNo": "LD-1457",
    "lastDateOfChange": null,
    "meterReading": null,
    "runningDifference": 29495,
    "description": "215-70-R 15",
    "remarks": null
  },
  {
    "registrationNo": "LD-2367",
    "lastDateOfChange": null,
    "meterReading": null,
    "runningDifference": 8829,
    "description": "215-70-R 15",
    "remarks": null
  },
  {
    "registrationNo": "LD-2368",
    "lastDateOfChange": null,
    "meterReading": null,
    "runningDifference": 9444,
    "description": "215-70-R 15",
    "remarks": null
  }
]